cli_grid.py
dota2_grid_editor_cli-1.1.0.dist-info/LICENSE
dota2_grid_editor_cli-1.1.0.dist-info/METADATA
dota2_grid_editor_cli-1.1.0.dist-info/WHEEL
dota2_grid_editor_cli-1.1.0.dist-info/entry_points.txt
dota2_grid_editor_cli-1.1.0.dist-info/top_level.txt
dota2_grid_editor_cli-1.1.0.dist-info/RECORD
