Metadata-Version: 2.1
Name: dota2-grid-editor-cli
Version: 1.1.0
Summary: CLI for dota2_grid_editor
Home-page: https://github.com/Psychewolf/dota2_grid_editor
Author: psyche_wolf
Author-email: jaforjaber@gmail.com
License: UNKNOWN
Platform: UNKNOWN
Classifier: Programming Language :: Python :: 3
Classifier: License :: OSI Approved :: MIT License
Classifier: Operating System :: OS Independent
Requires-Python: >=3.6
Requires-Dist: requests
Requires-Dist: pandas
